peewee_async/__init__.py
peewee_async/aio_model.py
peewee_async/connection.py
peewee_async/databases.py
peewee_async/pool.py
peewee_async/result_wrappers.py
peewee_async/signals.py
peewee_async/transactions.py
peewee_async/utils.py
peewee_async-1.2.0.dist-info/LICENSE
peewee_async-1.2.0.dist-info/METADATA
peewee_async-1.2.0.dist-info/WHEEL
peewee_async-1.2.0.dist-info/RECORD
