Metadata-Version: 2.3
Name: peewee-async
Version: 1.2.0
Summary: Asynchronous interface for peewee ORM powered by asyncio.
Author: Alexey Kinev
Author-email: rudy@05bit.com
Requires-Python: >=3.9,<4.0
Classifier: Programming Language :: Python :: 3
Classifier: Programming Language :: Python :: 3.9
Classifier: Programming Language :: Python :: 3.10
Classifier: Programming Language :: Python :: 3.11
Classifier: Programming Language :: Python :: 3.12
Classifier: Programming Language :: Python :: 3.13
Provides-Extra: develop
Provides-Extra: docs
Provides-Extra: mysql
Provides-Extra: postgresql
Provides-Extra: psycopg
Requires-Dist: aiomysql (>=0.2.0,<0.3.0) ; extra == "mysql" or extra == "develop" or extra == "docs"
Requires-Dist: aiopg (>=1.4.0,<2.0.0) ; extra == "postgresql" or extra == "develop" or extra == "docs"
Requires-Dist: cryptography (>=43.0.1,<44.0.0) ; extra == "mysql" or extra == "develop" or extra == "docs"
Requires-Dist: mypy (>=1.10.1,<2.0.0) ; extra == "develop"
Requires-Dist: peewee (>=3.15.4,<4.0.0)
Requires-Dist: psycopg (>=3.2.0,<4.0.0) ; extra == "develop" or extra == "psycopg"
Requires-Dist: psycopg-pool (>=3.2.0,<4.0.0) ; extra == "develop" or extra == "psycopg"
Requires-Dist: pytest (>=7.4.1,<8.0.0) ; extra == "develop"
Requires-Dist: pytest-asyncio (>=0.21.1,<0.22.0) ; extra == "develop"
Requires-Dist: pytest-mock (>=3.14.0,<4.0.0) ; extra == "develop"
Requires-Dist: sphinx (>=7.1.2,<8.0.0) ; extra == "docs"
Requires-Dist: sphinx-rtd-theme (>=1.3.0rc1,<2.0.0) ; extra == "docs"
Requires-Dist: types-PyMySQL (>=1.1.0.20240524,<2.0.0.0) ; extra == "develop"
Requires-Dist: typing-extensions (>=4.12.2,<5.0.0)
